<annotation>
	<folder/>
	<filename>government7.jpg</filename>
	<path>../images/government7.jpg</path>
	<source>
		<database>Unknown</database>
	</source>
	<size>
		<width>582</width>
		<height>342</height>
		<depth>3</depth>
	</size>
	<segmented>0</segmented>
	<object>
		<name>gov-plate</name>
		<pose>Unspecified</pose>
		<truncated>0</truncated>
		<difficult>0</difficult>
		<bndbox>
			<xmin>331</xmin>
			<ymin>196</ymin>
			<xmax>449</xmax>
			<ymax>237</ymax>
		</bndbox>
	</object>
</annotation>
